{
  "menuList": [{
    "primaryFieldValue": "34",
    "create_userid": null,
    "int_isdisable": null,
    "modify_datetime": "2018-04-03 07:41:50.0",
    "description": null,
    "sort_index": "1200",
    "leaf": false,
    "url": "#",
    "parent_menu_id": "0",
    "btn_counts": "0",
    "children": [{
      "primaryFieldValue": "87",
      "create_userid": null,
      "int_isdisable": null,
      "modify_datetime": "2018-09-06 11:47:08.0",
      "description": null,
      "sort_index": "10",
      "leaf": true,
      "url": "/manager/order_blm/list_order_blm.jsp",
      "parent_menu_id": "34",
      "btn_counts": "0",
      "children": [],
      "create_datetime": "2017-05-09 01:28:25.0",
      "menu_name": "订单列表",
      "modify_userid": "328",
      "int_disabled": "0",
      "data_qx": "",
      "menu_level": null,
      "btn_qx": "",
      "func_qx": 893,
      "menu_id": "87"
    }, {
      "primaryFieldValue": "164",
      "create_userid": "281",
      "int_isdisable": null,
      "modify_datetime": "2018-09-06 11:47:14.0",
      "description": null,
      "sort_index": "11",
      "leaf": true,
      "url": "/manager/order_blm/list_order_blm_refund.jsp",
      "parent_menu_id": "34",
      "btn_counts": "0",
      "children": [],
      "create_datetime": "2018-05-15 11:13:56.0",
      "menu_name": "退款列表",
      "modify_userid": "328",
      "int_disabled": "0",
      "data_qx": "",
      "menu_level": null,
      "btn_qx": "",
      "func_qx": 1898,
      "menu_id": "164"
    }],
    "create_datetime": null,
    "menu_name": "订单交易",
    "modify_userid": "1",
    "int_disabled": "0",
    "data_qx": "",
    "menu_level": "2",
    "btn_qx": "",
    "state": "open",
    "func_qx": 862,
    "menu_id": "34"
  }, {
    "primaryFieldValue": "137",
    "create_userid": "1",
    "int_isdisable": null,
    "modify_datetime": "2018-04-03 07:41:58.0",
    "description": null,
    "sort_index": "1300",
    "leaf": false,
    "url": "#",
    "parent_menu_id": "0",
    "btn_counts": "0",
    "children": [{
      "primaryFieldValue": "143",
      "create_userid": "1",
      "int_isdisable": null,
      "modify_datetime": "2018-09-06 11:49:02.0",
      "description": null,
      "sort_index": "10",
      "leaf": true,
      "url": "manager/machine_items/list_machine_items.jsp",
      "parent_menu_id": "137",
      "btn_counts": "0",
      "children": [],
      "create_datetime": "2017-12-25 08:49:55.0",
      "menu_name": "商品运营",
      "modify_userid": "328",
      "int_disabled": "0",
      "data_qx": "",
      "menu_level": null,
      "btn_qx": "",
      "func_qx": 1569,
      "menu_id": "143"
    }, {
      "primaryFieldValue": "144",
      "create_userid": "1",
      "int_isdisable": null,
      "modify_datetime": "2018-09-06 11:48:56.0",
      "description": null,
      "sort_index": "20",
      "leaf": true,
      "url": "manager/machine_items_group/list_machine_items_group.jsp",
      "parent_menu_id": "137",
      "btn_counts": "0",
      "children": [],
      "create_datetime": "2017-12-25 08:50:27.0",
      "menu_name": "模块管理",
      "modify_userid": "328",
      "int_disabled": "0",
      "data_qx": "",
      "menu_level": null,
      "btn_qx": "",
      "func_qx": 1570,
      "menu_id": "144"
    }, {
      "primaryFieldValue": "147",
      "create_userid": "1",
      "int_isdisable": null,
      "modify_datetime": "2018-09-06 11:48:42.0",
      "description": null,
      "sort_index": "21",
      "leaf": true,
      "url": "manager/items_group/list_items_group.jsp",
      "parent_menu_id": "137",
      "btn_counts": "0",
      "children": [],
      "create_datetime": "2017-12-27 04:15:26.0",
      "menu_name": "商品分类",
      "modify_userid": "328",
      "int_disabled": "0",
      "data_qx": "",
      "menu_level": null,
      "btn_qx": "",
      "func_qx": 1573,
      "menu_id": "147"
    }, {
      "primaryFieldValue": "145",
      "create_userid": "1",
      "int_isdisable": null,
      "modify_datetime": "2018-09-06 11:48:46.0",
      "description": null,
      "sort_index": "30",
      "leaf": true,
      "url": "manager/machine_ads/list_machine_ads.jsp",
      "parent_menu_id": "137",
      "btn_counts": "0",
      "children": [],
      "create_datetime": "2017-12-25 08:50:57.0",
      "menu_name": "广告运营",
      "modify_userid": "328",
      "int_disabled": "0",
      "data_qx": "",
      "menu_level": null,
      "btn_qx": "",
      "func_qx": 1571,
      "menu_id": "145"
    }, {
      "primaryFieldValue": "149",
      "create_userid": "1",
      "int_isdisable": null,
      "modify_datetime": "2018-09-06 11:48:22.0",
      "description": null,
      "sort_index": "40",
      "leaf": true,
      "url": "manager/cache/list_cache.jsp",
      "parent_menu_id": "137",
      "btn_counts": "0",
      "children": [],
      "create_datetime": "2018-01-02 14:20:39.0",
      "menu_name": "缓存管理",
      "modify_userid": "328",
      "int_disabled": "0",
      "data_qx": "",
      "menu_level": null,
      "btn_qx": "",
      "func_qx": 1575,
      "menu_id": "149"
    }],
    "create_datetime": "2017-12-01 18:27:02.0",
    "menu_name": "APP运营",
    "modify_userid": "1",
    "int_disabled": "0",
    "data_qx": "",
    "menu_level": null,
    "btn_qx": "",
    "state": "open",
    "func_qx": 1473,
    "menu_id": "137"
  }, {
    "primaryFieldValue": "131",
    "create_userid": "1",
    "int_isdisable": null,
    "modify_datetime": "2018-04-03 07:42:06.0",
    "description": null,
    "sort_index": "1400",
    "leaf": false,
    "url": "#",
    "parent_menu_id": "0",
    "btn_counts": "0",
    "children": [{
      "primaryFieldValue": "141",
      "create_userid": "1",
      "int_isdisable": null,
      "modify_datetime": "2018-09-06 11:49:55.0",
      "description": null,
      "sort_index": "10",
      "leaf": true,
      "url": "manager/channel/list_channel.jsp",
      "parent_menu_id": "131",
      "btn_counts": "0",
      "children": [],
      "create_datetime": "2017-12-21 14:18:28.0",
      "menu_name": "渠道列表",
      "modify_userid": "328",
      "int_disabled": "0",
      "data_qx": "",
      "menu_level": null,
      "btn_qx": "",
      "func_qx": 1567,
      "menu_id": "141"
    }, {
      "primaryFieldValue": "158",
      "create_userid": "1",
      "int_isdisable": null,
      "modify_datetime": "2018-09-06 11:50:17.0",
      "description": null,
      "sort_index": "11",
      "leaf": true,
      "url": "sto/suppliers/list_suppliers_appid.jsp",
      "parent_menu_id": "131",
      "btn_counts": "0",
      "children": [],
      "create_datetime": "2018-04-03 07:47:32.0",
      "menu_name": "供应商",
      "modify_userid": "328",
      "int_disabled": "0",
      "data_qx": "",
      "menu_level": null,
      "btn_qx": "",
      "func_qx": 1688,
      "menu_id": "158"
    }, {
      "primaryFieldValue": "185",
      "create_userid": "311",
      "int_isdisable": null,
      "modify_datetime": "2018-09-06 11:51:32.0",
      "description": null,
      "sort_index": "20",
      "leaf": true,
      "url": "sto/shops/list_shops.jsp",
      "parent_menu_id": "131",
      "btn_counts": "0",
      "children": [],
      "create_datetime": "2018-08-08 18:25:23.0",
      "menu_name": "门店列表",
      "modify_userid": "328",
      "int_disabled": "0",
      "data_qx": "",
      "menu_level": null,
      "btn_qx": "",
      "func_qx": 2742,
      "menu_id": "185"
    }, {
      "primaryFieldValue": "182",
      "create_userid": "311",
      "int_isdisable": null,
      "modify_datetime": "2018-09-06 11:51:40.0",
      "description": null,
      "sort_index": "21",
      "leaf": true,
      "url": "sto/material_type/list_material_type.jsp",
      "parent_menu_id": "131",
      "btn_counts": "0",
      "children": [],
      "create_datetime": "2018-08-08 18:23:26.0",
      "menu_name": "物料分类",
      "modify_userid": "328",
      "int_disabled": "0",
      "data_qx": "",
      "menu_level": null,
      "btn_qx": "",
      "func_qx": 2739,
      "menu_id": "182"
    }, {
      "primaryFieldValue": "183",
      "create_userid": "311",
      "int_isdisable": null,
      "modify_datetime": "2018-09-06 11:51:47.0",
      "description": null,
      "sort_index": "22",
      "leaf": true,
      "url": "sto/material/list_material.jsp",
      "parent_menu_id": "131",
      "btn_counts": "0",
      "children": [],
      "create_datetime": "2018-08-08 18:24:07.0",
      "menu_name": "物料清单",
      "modify_userid": "328",
      "int_disabled": "0",
      "data_qx": "",
      "menu_level": null,
      "btn_qx": "",
      "func_qx": 2740,
      "menu_id": "183"
    }, {
      "primaryFieldValue": "146",
      "create_userid": "1",
      "int_isdisable": null,
      "modify_datetime": "2018-09-06 11:52:05.0",
      "description": null,
      "sort_index": "30",
      "leaf": true,
      "url": "sto/item_type/list_item_type.jsp",
      "parent_menu_id": "131",
      "btn_counts": "0",
      "children": [],
      "create_datetime": "2017-12-25 08:51:06.0",
      "menu_name": "商品分类",
      "modify_userid": "328",
      "int_disabled": "0",
      "data_qx": "",
      "menu_level": null,
      "btn_qx": "",
      "func_qx": 1572,
      "menu_id": "146"
    }, {
      "primaryFieldValue": "176",
      "create_userid": "424",
      "int_isdisable": null,
      "modify_datetime": "2018-09-06 11:52:41.0",
      "description": null,
      "sort_index": "32",
      "leaf": true,
      "url": "sto/items/list_items.jsp?standard_flag=1",
      "parent_menu_id": "131",
      "btn_counts": "0",
      "children": [],
      "create_datetime": "2018-08-08 17:58:04.0",
      "menu_name": "商品-标品列表",
      "modify_userid": "328",
      "int_disabled": "0",
      "data_qx": "",
      "menu_level": null,
      "btn_qx": "",
      "func_qx": 2733,
      "menu_id": "176"
    }, {
      "primaryFieldValue": "177",
      "create_userid": "424",
      "int_isdisable": null,
      "modify_datetime": "2018-09-06 11:52:48.0",
      "description": null,
      "sort_index": "33",
      "leaf": true,
      "url": "sto/items/list_items.jsp?standard_flag=0",
      "parent_menu_id": "131",
      "btn_counts": "0",
      "children": [],
      "create_datetime": "2018-08-08 17:59:51.0",
      "menu_name": "商品-非标列表",
      "modify_userid": "328",
      "int_disabled": "0",
      "data_qx": "",
      "menu_level": null,
      "btn_qx": "",
      "func_qx": 2734,
      "menu_id": "177"
    }, {
      "primaryFieldValue": "148",
      "create_userid": "1",
      "int_isdisable": null,
      "modify_datetime": "2018-09-06 11:53:10.0",
      "description": null,
      "sort_index": "40",
      "leaf": true,
      "url": "manager/ads/list_ads.jsp",
      "parent_menu_id": "131",
      "btn_counts": "0",
      "children": [],
      "create_datetime": "2017-12-29 10:31:09.0",
      "menu_name": "广告管理",
      "modify_userid": "328",
      "int_disabled": null,
      "data_qx": "",
      "menu_level": null,
      "btn_qx": "",
      "func_qx": 1574,
      "menu_id": "148"
    }, {
      "primaryFieldValue": "163",
      "create_userid": "340",
      "int_isdisable": null,
      "modify_datetime": "2018-09-06 11:53:17.0",
      "description": null,
      "sort_index": "50",
      "leaf": true,
      "url": "manager/activity_info/list_activity_info.jsp",
      "parent_menu_id": "131",
      "btn_counts": "0",
      "children": [],
      "create_datetime": "2018-04-27 13:40:13.0",
      "menu_name": "活动配置",
      "modify_userid": "328",
      "int_disabled": "0",
      "data_qx": "",
      "menu_level": null,
      "btn_qx": "",
      "func_qx": 1798,
      "menu_id": "163"
    }],
    "create_datetime": "2017-11-17 20:56:49.0",
    "menu_name": "运营管理",
    "modify_userid": "1",
    "int_disabled": "0",
    "data_qx": "",
    "menu_level": null,
    "btn_qx": "",
    "state": "open",
    "func_qx": 1429,
    "menu_id": "131"
  }, {
    "primaryFieldValue": "91",
    "create_userid": null,
    "int_isdisable": null,
    "modify_datetime": "2018-04-03 07:42:13.0",
    "description": null,
    "sort_index": "1500",
    "leaf": false,
    "url": "#",
    "parent_menu_id": "0",
    "btn_counts": "0",
    "children": [{
      "primaryFieldValue": "184",
      "create_userid": "311",
      "int_isdisable": null,
      "modify_datetime": "2018-09-07 14:57:33.0",
      "description": null,
      "sort_index": "10",
      "leaf": true,
      "url": "sto/machine_model/list_machine_model.jsp",
      "parent_menu_id": "91",
      "btn_counts": "0",
      "children": [],
      "create_datetime": "2018-08-08 18:24:55.0",
      "menu_name": "设备型号",
      "modify_userid": "273",
      "int_disabled": "0",
      "data_qx": "",
      "menu_level": null,
      "btn_qx": "",
      "func_qx": 2741,
      "menu_id": "184"
    }, {
      "primaryFieldValue": "140",
      "create_userid": "1",
      "int_isdisable": null,
      "modify_datetime": "2018-09-06 11:54:53.0",
      "description": null,
      "sort_index": "21",
      "leaf": true,
      "url": "sto/machines/list_machines_standard.jsp",
      "parent_menu_id": "91",
      "btn_counts": "0",
      "children": [],
      "create_datetime": "2017-12-03 10:18:06.0",
      "menu_name": "设备-标品机",
      "modify_userid": "328",
      "int_disabled": "0",
      "data_qx": "",
      "menu_level": null,
      "btn_qx": "",
      "func_qx": 1503,
      "menu_id": "140"
    }, {
      "primaryFieldValue": "171",
      "create_userid": "369",
      "int_isdisable": null,
      "modify_datetime": "2018-09-06 11:55:12.0",
      "description": null,
      "sort_index": "22",
      "leaf": true,
      "url": "sto/machines/list_machines_unstandard.jsp",
      "parent_menu_id": "91",
      "btn_counts": "0",
      "children": [],
      "create_datetime": "2018-05-24 16:22:13.0",
      "menu_name": "设备-非标机",
      "modify_userid": "328",
      "int_disabled": "0",
      "data_qx": "",
      "menu_level": null,
      "btn_qx": "",
      "func_qx": 1974,
      "menu_id": "171"
    }, {
      "primaryFieldValue": "150",
      "create_userid": "1",
      "int_isdisable": null,
      "modify_datetime": "2018-09-06 11:55:34.0",
      "description": null,
      "sort_index": "30",
      "leaf": true,
      "url": "/manager/vi_machine_errors/list_vi_machine_errors.jsp",
      "parent_menu_id": "91",
      "btn_counts": "0",
      "children": [],
      "create_datetime": "2018-03-07 18:32:39.0",
      "menu_name": "故障码管理",
      "modify_userid": "328",
      "int_disabled": "0",
      "data_qx": "",
      "menu_level": null,
      "btn_qx": "",
      "func_qx": 1678,
      "menu_id": "150"
    }, {
      "primaryFieldValue": "151",
      "create_userid": "1",
      "int_isdisable": null,
      "modify_datetime": "2018-09-06 11:55:45.0",
      "description": null,
      "sort_index": "31",
      "leaf": true,
      "url": "/manager/vi_other_message/list_vi_other_message.jsp",
      "parent_menu_id": "91",
      "btn_counts": "0",
      "children": [],
      "create_datetime": "2018-03-07 18:33:20.0",
      "menu_name": "故障处理记录",
      "modify_userid": "328",
      "int_disabled": "0",
      "data_qx": "",
      "menu_level": null,
      "btn_qx": "",
      "func_qx": 1679,
      "menu_id": "151"
    }, {
      "primaryFieldValue": "162",
      "create_userid": "1",
      "int_isdisable": null,
      "modify_datetime": "2018-05-11 22:27:46.0",
      "description": null,
      "sort_index": "51",
      "leaf": true,
      "url": "manager/vi_machine_status_auto/list_vi_machine_status_auto.jsp",
      "parent_menu_id": "91",
      "btn_counts": "0",
      "children": [],
      "create_datetime": "2018-04-03 07:48:40.0",
      "menu_name": "状态记录",
      "modify_userid": "340",
      "int_disabled": "0",
      "data_qx": "",
      "menu_level": null,
      "btn_qx": "",
      "func_qx": 1692,
      "menu_id": "162"
    }],
    "create_datetime": "2017-05-09 01:29:32.0",
    "menu_name": "设备管理",
    "modify_userid": "1",
    "int_disabled": "0",
    "data_qx": "",
    "menu_level": null,
    "btn_qx": "",
    "state": "open",
    "func_qx": 897,
    "menu_id": "91"
  }, {
    "primaryFieldValue": "138",
    "create_userid": "1",
    "int_isdisable": null,
    "modify_datetime": "2018-06-05 11:28:49.0",
    "description": null,
    "sort_index": "1800",
    "leaf": false,
    "url": "#",
    "parent_menu_id": "0",
    "btn_counts": "0",
    "children": [{
      "primaryFieldValue": "152",
      "create_userid": "1",
      "int_isdisable": null,
      "modify_datetime": "2018-09-06 10:32:14.0",
      "description": "form/form_replenishment/list_form_replenishment.jsp",
      "sort_index": "1",
      "leaf": true,
      "url": "sto/shop_replenish_splitform/list_shop_replenish_splitform.jsp",
      "parent_menu_id": "138",
      "btn_counts": "0",
      "children": [],
      "create_datetime": "2018-04-03 07:44:28.0",
      "menu_name": "门仓补货单",
      "modify_userid": "328",
      "int_disabled": "0",
      "data_qx": "",
      "menu_level": null,
      "btn_qx": "",
      "func_qx": 1682,
      "menu_id": "152"
    }, {
      "primaryFieldValue": "153",
      "create_userid": "1",
      "int_isdisable": null,
      "modify_datetime": "2018-09-06 10:33:08.0",
      "description": "配送单form/form_replenishment/list_form_replenishment_chu_ku.jsp",
      "sort_index": "2",
      "leaf": true,
      "url": "sto/city_replenish_form/list_city_replenish_form.jsp",
      "parent_menu_id": "138",
      "btn_counts": "0",
      "children": [],
      "create_datetime": "2018-04-03 07:44:52.0",
      "menu_name": "城仓补货单",
      "modify_userid": "328",
      "int_disabled": "0",
      "data_qx": "",
      "menu_level": null,
      "btn_qx": "",
      "func_qx": 1683,
      "menu_id": "153"
    }, {
      "primaryFieldValue": "165",
      "create_userid": "369",
      "int_isdisable": null,
      "modify_datetime": "2018-09-06 10:34:14.0",
      "description": null,
      "sort_index": "3",
      "leaf": true,
      "url": "sto/store_receive_form/list_store_receive_form.jsp",
      "parent_menu_id": "138",
      "btn_counts": "0",
      "children": [],
      "create_datetime": "2018-05-24 16:19:11.0",
      "menu_name": "门仓收货单",
      "modify_userid": "328",
      "int_disabled": "0",
      "data_qx": "",
      "menu_level": null,
      "btn_qx": "",
      "func_qx": 1968,
      "menu_id": "165"
    }, {
      "primaryFieldValue": "154",
      "create_userid": "1",
      "int_isdisable": null,
      "modify_datetime": "2018-09-06 10:35:19.0",
      "description": null,
      "sort_index": "4",
      "leaf": true,
      "url": "sto/city_receive_form/list_city_receive_form.jsp",
      "parent_menu_id": "138",
      "btn_counts": "0",
      "children": [],
      "create_datetime": "2018-04-03 07:45:21.0",
      "menu_name": "城仓收货单",
      "modify_userid": "328",
      "int_disabled": "0",
      "data_qx": "",
      "menu_level": null,
      "btn_qx": "",
      "func_qx": 1684,
      "menu_id": "154"
    }, {
      "primaryFieldValue": "156",
      "create_userid": "1",
      "int_isdisable": null,
      "modify_datetime": "2018-09-06 10:36:08.0",
      "description": null,
      "sort_index": "6",
      "leaf": true,
      "url": "sto/store_send_form/list_store_send_form.jsp",
      "parent_menu_id": "138",
      "btn_counts": "0",
      "children": [],
      "create_datetime": "2018-04-03 07:46:12.0",
      "menu_name": "仓库配送单",
      "modify_userid": "328",
      "int_disabled": "0",
      "data_qx": "",
      "menu_level": null,
      "btn_qx": "",
      "func_qx": 1686,
      "menu_id": "156"
    }, {
      "primaryFieldValue": "155",
      "create_userid": "1",
      "int_isdisable": null,
      "modify_datetime": "2018-09-06 10:36:45.0",
      "description": null,
      "sort_index": "7",
      "leaf": true,
      "url": "sto/purchase_goods_form/list_purchase_goods_form.jsp",
      "parent_menu_id": "138",
      "btn_counts": "0",
      "children": [],
      "create_datetime": "2018-04-03 07:45:51.0",
      "menu_name": "采销订货单",
      "modify_userid": "328",
      "int_disabled": "0",
      "data_qx": "",
      "menu_level": null,
      "btn_qx": "",
      "func_qx": 1685,
      "menu_id": "155"
    }, {
      "primaryFieldValue": "157",
      "create_userid": "1",
      "int_isdisable": null,
      "modify_datetime": "2018-09-06 10:37:06.0",
      "description": null,
      "sort_index": "20",
      "leaf": true,
      "url": "sto/requisition_form/list_requisition_form.jsp",
      "parent_menu_id": "138",
      "btn_counts": "0",
      "children": [],
      "create_datetime": "2018-04-03 07:46:30.0",
      "menu_name": "仓库调拨单",
      "modify_userid": "328",
      "int_disabled": "0",
      "data_qx": "",
      "menu_level": null,
      "btn_qx": "",
      "func_qx": 1687,
      "menu_id": "157"
    }, {
      "primaryFieldValue": "166",
      "create_userid": "369",
      "int_isdisable": null,
      "modify_datetime": "2018-09-06 10:37:35.0",
      "description": null,
      "sort_index": "21",
      "leaf": true,
      "url": "sto/refund_form/list_refund_form.jsp",
      "parent_menu_id": "138",
      "btn_counts": "0",
      "children": [],
      "create_datetime": "2018-05-24 16:19:47.0",
      "menu_name": "仓库退货单",
      "modify_userid": "328",
      "int_disabled": "0",
      "data_qx": "",
      "menu_level": null,
      "btn_qx": "",
      "func_qx": 1969,
      "menu_id": "166"
    }, {
      "primaryFieldValue": "167",
      "create_userid": "369",
      "int_isdisable": null,
      "modify_datetime": "2018-09-06 10:37:59.0",
      "description": null,
      "sort_index": "30",
      "leaf": true,
      "url": "sto/damage_form/list_damage_form.jsp",
      "parent_menu_id": "138",
      "btn_counts": "0",
      "children": [],
      "create_datetime": "2018-05-24 16:20:16.0",
      "menu_name": "仓库报损单",
      "modify_userid": "328",
      "int_disabled": "0",
      "data_qx": "",
      "menu_level": null,
      "btn_qx": "",
      "func_qx": 1970,
      "menu_id": "167"
    }],
    "create_datetime": "2017-12-01 18:27:10.0",
    "menu_name": "采购管理",
    "modify_userid": "328",
    "int_disabled": "0",
    "data_qx": "",
    "menu_level": null,
    "btn_qx": "",
    "state": "open",
    "func_qx": 1474,
    "menu_id": "138"
  }, {
    "primaryFieldValue": "132",
    "create_userid": "1",
    "int_isdisable": null,
    "modify_datetime": "2018-09-06 10:58:05.0",
    "description": null,
    "sort_index": "1900",
    "leaf": false,
    "url": "#",
    "parent_menu_id": "0",
    "btn_counts": "0",
    "children": [{
      "primaryFieldValue": "175",
      "create_userid": "369",
      "int_isdisable": null,
      "modify_datetime": "2018-09-06 14:50:02.0",
      "description": null,
      "sort_index": "10",
      "leaf": true,
      "url": "sto/distribution_center/list_distribution_center.jsp",
      "parent_menu_id": "132",
      "btn_counts": "0",
      "children": [],
      "create_datetime": "2018-05-24 16:26:45.0",
      "menu_name": "配送中心管理",
      "modify_userid": "328",
      "int_disabled": "0",
      "data_qx": "",
      "menu_level": null,
      "btn_qx": "",
      "func_qx": 1978,
      "menu_id": "175"
    }, {
      "primaryFieldValue": "102",
      "create_userid": null,
      "int_isdisable": null,
      "modify_datetime": "2018-09-06 11:17:05.0",
      "description": null,
      "sort_index": "11",
      "leaf": true,
      "url": "sto/form_store/list_form_store.jsp",
      "parent_menu_id": "132",
      "btn_counts": "0",
      "children": [],
      "create_datetime": "2017-05-09 01:39:17.0",
      "menu_name": "仓库管理",
      "modify_userid": "328",
      "int_disabled": "0",
      "data_qx": "",
      "menu_level": null,
      "btn_qx": "",
      "func_qx": 908,
      "menu_id": "102"
    }, {
      "primaryFieldValue": "159",
      "create_userid": "1",
      "int_isdisable": null,
      "modify_datetime": "2018-09-06 10:59:31.0",
      "description": null,
      "sort_index": "20",
      "leaf": true,
      "url": "sto/store_material_inventory/list_store_material_inventory.jsp",
      "parent_menu_id": "132",
      "btn_counts": "0",
      "children": [],
      "create_datetime": "2018-04-03 07:47:49.0",
      "menu_name": "库存统计",
      "modify_userid": "328",
      "int_disabled": "0",
      "data_qx": "",
      "menu_level": null,
      "btn_qx": "",
      "func_qx": 1689,
      "menu_id": "159"
    }, {
      "primaryFieldValue": "199",
      "create_userid": "311",
      "int_isdisable": null,
      "modify_datetime": "2018-09-06 11:01:18.0",
      "description": null,
      "sort_index": "40",
      "leaf": true,
      "url": "/sto/stock/stockconfigure.jsp",
      "parent_menu_id": "132",
      "btn_counts": "0",
      "children": [],
      "create_datetime": "2018-08-28 15:59:22.0",
      "menu_name": "盘点配置",
      "modify_userid": "328",
      "int_disabled": "0",
      "data_qx": "",
      "menu_level": null,
      "btn_qx": "",
      "func_qx": 2756,
      "menu_id": "199"
    }, {
      "primaryFieldValue": "200",
      "create_userid": "311",
      "int_isdisable": null,
      "modify_datetime": "2018-09-06 11:01:39.0",
      "description": null,
      "sort_index": "41",
      "leaf": true,
      "url": "/sto/take_stock_form/take_stock_form.jsp",
      "parent_menu_id": "132",
      "btn_counts": "0",
      "children": [],
      "create_datetime": "2018-08-30 17:28:45.0",
      "menu_name": "盘点审核",
      "modify_userid": "328",
      "int_disabled": "0",
      "data_qx": "",
      "menu_level": null,
      "btn_qx": "",
      "func_qx": 2757,
      "menu_id": "200"
    }, {
      "primaryFieldValue": "201",
      "create_userid": "311",
      "int_isdisable": null,
      "modify_datetime": "2018-09-06 11:01:48.0",
      "description": null,
      "sort_index": "42",
      "leaf": true,
      "url": "/sto/take_stock_form/take_stock_form_all.jsp",
      "parent_menu_id": "132",
      "btn_counts": "0",
      "children": [],
      "create_datetime": "2018-08-31 17:40:48.0",
      "menu_name": "盘点列表",
      "modify_userid": "328",
      "int_disabled": "0",
      "data_qx": "",
      "menu_level": null,
      "btn_qx": "",
      "func_qx": 2758,
      "menu_id": "201"
    }, {
      "primaryFieldValue": "168",
      "create_userid": "369",
      "int_isdisable": null,
      "modify_datetime": "2018-09-06 11:56:51.0",
      "description": null,
      "sort_index": "50",
      "leaf": true,
      "url": "sto/io_store_history/list_io_store_history.jsp",
      "parent_menu_id": "132",
      "btn_counts": "0",
      "children": [],
      "create_datetime": "2018-05-24 16:20:47.0",
      "menu_name": "出入库记录",
      "modify_userid": "328",
      "int_disabled": "0",
      "data_qx": "",
      "menu_level": null,
      "btn_qx": "",
      "func_qx": 1971,
      "menu_id": "168"
    }, {
      "primaryFieldValue": "160",
      "create_userid": "1",
      "int_isdisable": null,
      "modify_datetime": "2018-09-06 11:56:58.0",
      "description": null,
      "sort_index": "51",
      "leaf": true,
      "url": "sto/io_store_history_detail/list_io_store_history_detail_in.jsp",
      "parent_menu_id": "132",
      "btn_counts": "0",
      "children": [],
      "create_datetime": "2018-04-03 07:48:05.0",
      "menu_name": "入库记录",
      "modify_userid": "328",
      "int_disabled": "0",
      "data_qx": "",
      "menu_level": null,
      "btn_qx": "",
      "func_qx": 1690,
      "menu_id": "160"
    }, {
      "primaryFieldValue": "174",
      "create_userid": "369",
      "int_isdisable": null,
      "modify_datetime": "2018-09-06 11:57:07.0",
      "description": null,
      "sort_index": "52",
      "leaf": true,
      "url": "sto/io_store_history_detail/list_io_store_history_detail_out.jsp",
      "parent_menu_id": "132",
      "btn_counts": "0",
      "children": [],
      "create_datetime": "2018-05-24 16:24:12.0",
      "menu_name": "出库记录",
      "modify_userid": "328",
      "int_disabled": "0",
      "data_qx": "",
      "menu_level": null,
      "btn_qx": "",
      "func_qx": 1977,
      "menu_id": "174"
    }, {
      "primaryFieldValue": "135",
      "create_userid": "1",
      "int_isdisable": null,
      "modify_datetime": "2018-09-06 11:57:18.0",
      "description": null,
      "sort_index": "53",
      "leaf": true,
      "url": "manager/vi_machine_rows_add/list_vi_machine_rows_add.jsp",
      "parent_menu_id": "132",
      "btn_counts": "0",
      "children": [],
      "create_datetime": "2017-12-01 18:26:30.0",
      "menu_name": "上料明细(视图)",
      "modify_userid": "328",
      "int_disabled": "0",
      "data_qx": "",
      "menu_level": null,
      "btn_qx": "",
      "func_qx": 1471,
      "menu_id": "135"
    }],
    "create_datetime": "2017-11-29 18:57:36.0",
    "menu_name": "仓库管理",
    "modify_userid": "328",
    "int_disabled": "0",
    "data_qx": "",
    "menu_level": null,
    "btn_qx": "",
    "state": "open",
    "func_qx": 1468,
    "menu_id": "132"
  }, {
    "primaryFieldValue": "6",
    "create_userid": null,
    "int_isdisable": null,
    "modify_datetime": "2018-09-06 13:49:20.0",
    "description": null,
    "sort_index": "8888",
    "leaf": false,
    "url": "#",
    "parent_menu_id": "0",
    "btn_counts": "0",
    "children": [{
      "primaryFieldValue": "26",
      "create_userid": null,
      "int_isdisable": null,
      "modify_datetime": "2017-11-16 17:48:02.0",
      "description": null,
      "sort_index": "0",
      "leaf": true,
      "url": "/system/user/list.jsp",
      "parent_menu_id": "6",
      "btn_counts": "0",
      "children": [],
      "create_datetime": null,
      "menu_name": "账号管理",
      "modify_userid": "1",
      "int_disabled": "0",
      "data_qx": "",
      "menu_level": "2",
      "btn_qx": "",
      "func_qx": 856,
      "menu_id": "26"
    }, {
      "primaryFieldValue": "27",
      "create_userid": null,
      "int_isdisable": null,
      "modify_datetime": "2017-11-16 17:48:03.0",
      "description": null,
      "sort_index": "31",
      "leaf": true,
      "url": "/system/user/pwd.jsp",
      "parent_menu_id": "6",
      "btn_counts": "0",
      "children": [],
      "create_datetime": null,
      "menu_name": "修改密码",
      "modify_userid": "1",
      "int_disabled": "0",
      "data_qx": "",
      "menu_level": "2",
      "btn_qx": "",
      "func_qx": 857,
      "menu_id": "27"
    }],
    "create_datetime": null,
    "menu_name": "账号管理",
    "modify_userid": "328",
    "int_disabled": "0",
    "data_qx": "",
    "menu_level": "0",
    "btn_qx": "",
    "state": "open",
    "func_qx": 855,
    "menu_id": "6"
  }, {
    "primaryFieldValue": "50",
    "create_userid": null,
    "int_isdisable": null,
    "modify_datetime": "2018-04-03 07:42:36.0",
    "description": null,
    "sort_index": "9999",
    "leaf": false,
    "url": "#",
    "parent_menu_id": "0",
    "btn_counts": "0",
    "children": [{
      "primaryFieldValue": "63",
      "create_userid": null,
      "int_isdisable": null,
      "modify_datetime": "2017-04-16 15:41:42.0",
      "description": null,
      "sort_index": "3",
      "leaf": true,
      "url": "/system/menu/list_tree.jsp",
      "parent_menu_id": "50",
      "btn_counts": "0",
      "children": [],
      "create_datetime": "2016-12-30 11:35:19.0",
      "menu_name": "菜单管理",
      "modify_userid": null,
      "int_disabled": null,
      "data_qx": "",
      "menu_level": "2",
      "btn_qx": "",
      "func_qx": 866,
      "menu_id": "63"
    }, {
      "primaryFieldValue": "29",
      "create_userid": null,
      "int_isdisable": null,
      "modify_datetime": "2017-05-09 04:26:34.0",
      "description": null,
      "sort_index": "31",
      "leaf": true,
      "url": "/system/role/list.jsp",
      "parent_menu_id": "50",
      "btn_counts": "0",
      "children": [],
      "create_datetime": null,
      "menu_name": "角色管理",
      "modify_userid": null,
      "int_disabled": null,
      "data_qx": "",
      "menu_level": "2",
      "btn_qx": "",
      "func_qx": 859,
      "menu_id": "29"
    }, {
      "primaryFieldValue": "28",
      "create_userid": null,
      "int_isdisable": null,
      "modify_datetime": "2017-05-09 04:26:56.0",
      "description": null,
      "sort_index": "311",
      "leaf": true,
      "url": "/system/para/list_both.jsp",
      "parent_menu_id": "50",
      "btn_counts": "0",
      "children": [],
      "create_datetime": null,
      "menu_name": "数据字典",
      "modify_userid": null,
      "int_disabled": null,
      "data_qx": "",
      "menu_level": "2",
      "btn_qx": "",
      "func_qx": 858,
      "menu_id": "28"
    }],
    "create_datetime": "2016-12-08 10:56:42.0",
    "menu_name": "功能权限",
    "modify_userid": "1",
    "int_disabled": "0",
    "data_qx": "",
    "menu_level": "2",
    "btn_qx": "",
    "state": "open",
    "func_qx": 864,
    "menu_id": "50"
  }, {
    "primaryFieldValue": "195",
    "create_userid": "328",
    "int_isdisable": null,
    "modify_datetime": "2018-08-22 20:57:04.0",
    "description": null,
    "sort_index": "1000000",
    "leaf": false,
    "url": null,
    "parent_menu_id": "0",
    "btn_counts": "0",
    "children": [{
      "primaryFieldValue": "197",
      "create_userid": "328",
      "int_isdisable": null,
      "modify_datetime": "2018-08-24 08:59:28.0",
      "description": null,
      "sort_index": "1",
      "leaf": true,
      "url": "bill/order_bill/list_order_bill.jsp",
      "parent_menu_id": "195",
      "btn_counts": "0",
      "children": [],
      "create_datetime": "2018-08-24 08:59:28.0",
      "menu_name": "对账单",
      "modify_userid": null,
      "int_disabled": null,
      "data_qx": "",
      "menu_level": null,
      "btn_qx": "",
      "func_qx": 2754,
      "menu_id": "197"
    }, {
      "primaryFieldValue": "196",
      "create_userid": "328",
      "int_isdisable": null,
      "modify_datetime": "2018-08-24 00:20:31.0",
      "description": null,
      "sort_index": "1",
      "leaf": true,
      "url": "/bill/channel_contract/list_channel_contract.jsp",
      "parent_menu_id": "195",
      "btn_counts": "0",
      "children": [],
      "create_datetime": "2018-08-22 20:58:12.0",
      "menu_name": "渠道合同管理",
      "modify_userid": "328",
      "int_disabled": "0",
      "data_qx": "",
      "menu_level": null,
      "btn_qx": "",
      "func_qx": 2753,
      "menu_id": "196"
    }],
    "create_datetime": "2018-08-22 20:55:41.0",
    "menu_name": "开发中-Jack",
    "modify_userid": "328",
    "int_disabled": "0",
    "data_qx": "",
    "menu_level": null,
    "btn_qx": "",
    "state": "open",
    "func_qx": 2752,
    "menu_id": "195"
  }]
}
